helm_values_generator/__init__.py
helm_values_generator/__main__.py
helm_values_generator/generate_values.py
helm_values_generator-0.1.0.dist-info/LICENSE
helm_values_generator-0.1.0.dist-info/METADATA
helm_values_generator-0.1.0.dist-info/WHEEL
helm_values_generator-0.1.0.dist-info/entry_points.txt
helm_values_generator-0.1.0.dist-info/top_level.txt
helm_values_generator-0.1.0.dist-info/RECORD
