Metadata-Version: 2.1
Name: helm-values-generator
Version: 0.1.0
Summary: Small tool to generate simple values template yaml from helm charts
Author-email: Liudas Sodonis <liudas.cloud.dev@gmail.com>
Classifier: Programming Language :: Python :: 3
Classifier: Operating System :: OS Independent
Classifier: Intended Audience :: Developers
Requires-Python: >=3.7
License-File: LICENSE
